jupyterlab_new_launcher/__init__.py
jupyterlab_new_launcher/_version.py
jupyterlab_new_launcher/handlers.py
jupyterlab_new_launcher-0.5.1.data/data/etc/jupyter/jupyter_server_config.d/jupyterlab_new_launcher.json
jupyterlab_new_launcher-0.5.1.data/data/share/jupyter/labextensions/jupyterlab-new-launcher/package.json
jupyterlab_new_launcher-0.5.1.data/data/share/jupyter/labextensions/jupyterlab-new-launcher/schemas/jupyterlab-new-launcher/package.json.orig
jupyterlab_new_launcher-0.5.1.data/data/share/jupyter/labextensions/jupyterlab-new-launcher/schemas/jupyterlab-new-launcher/plugin.json
jupyterlab_new_launcher-0.5.1.data/data/share/jupyter/labextensions/jupyterlab-new-launcher/static/728.3f83aed91468be09385a.js
jupyterlab_new_launcher-0.5.1.data/data/share/jupyter/labextensions/jupyterlab-new-launcher/static/930.f0073cf1dc37de476ce4.js
jupyterlab_new_launcher-0.5.1.data/data/share/jupyter/labextensions/jupyterlab-new-launcher/static/remoteEntry.c4a5bbb04bca8ebf6b67.js
jupyterlab_new_launcher-0.5.1.data/data/share/jupyter/labextensions/jupyterlab-new-launcher/static/style.js
jupyterlab_new_launcher-0.5.1.data/data/share/jupyter/labextensions/jupyterlab-new-launcher/static/third-party-licenses.json
jupyterlab_new_launcher-0.5.1.data/data/share/jupyter/labextensions/jupyterlab-new-launcher/install.json
jupyterlab_new_launcher-0.5.1.dist-info/METADATA
jupyterlab_new_launcher-0.5.1.dist-info/WHEEL
jupyterlab_new_launcher-0.5.1.dist-info/licenses/LICENSE
jupyterlab_new_launcher-0.5.1.dist-info/RECORD
