Metadata-Version: 2.3
Name: jupyterlab-new-launcher
Version: 0.5.1
Dynamic: Keywords
Summary: A redesigned JupyterLab launcher
Project-URL: Homepage, https://github.com/nebari-dev/jupyterlab-new-launcher
Project-URL: Bug Tracker, https://github.com/nebari-dev/jupyterlab-new-launcher/issues
Project-URL: Repository, https://github.com/nebari-dev/jupyterlab-new-launcher.git
Author-email: Nebari development team <internal-it@quansight.com>
License: BSD 3-Clause License
License-File: LICENSE
Classifier: Framework :: Jupyter
Classifier: Framework :: Jupyter :: JupyterLab
Classifier: Framework :: Jupyter :: JupyterLab :: 4
Classifier: Framework :: Jupyter :: JupyterLab :: Extensions
Classifier: Framework :: Jupyter :: JupyterLab :: Extensions :: Prebuilt
Classifier: License :: OSI Approved :: BSD License
Classifier: Programming Language :: Python
Classifier: Programming Language :: Python :: 3
Classifier: Programming Language :: Python :: 3.8
Classifier: Programming Language :: Python :: 3.9
Classifier: Programming Language :: Python :: 3.10
Classifier: Programming Language :: Python :: 3.11
Classifier: Programming Language :: Python :: 3.12
Requires-Python: >=3.8
Requires-Dist: jupyter-server<3,>=2.0.1
